assets/colorgrid.png
assets/grid3D.mtl
assets/grid3D.obj
assets/primitives.mtl
assets/primitives.obj
assets/uvgrid.png
assets/white.png
ratcave/__init__.py
ratcave/camera.py
ratcave/collision.py
ratcave/coordinates.py
ratcave/experimental.py
ratcave/fbo.py
ratcave/gl_states.py
ratcave/light.py
ratcave/materials.py
ratcave/mesh.py
ratcave/physical.py
ratcave/resources.py
ratcave/scene.py
ratcave/scenegraph.py
ratcave/shader.py
ratcave/texture.py
ratcave/vertex.py
ratcave/wavefront.py
ratcave/utils/__init__.py
ratcave/utils/gl.py
ratcave/utils/mixins.py
ratcave/utils/observers.py
shaders/cube/cubeShader.frag
shaders/cube/cubeShader.vert
shaders/default/combShader.frag
shaders/default/combShader.vert
shaders/deferred/basicDeferred.frag
shaders/deferred/basicDeferred.vert
shaders/shadow/shadowShader.frag
shaders/shadow/shadowShader.vert
tests/__init__.py
tests/run.py
tests/test_camera.py
tests/test_coordinates.py
tests/test_drawable.py
tests/test_glutils.py
tests/test_meshes.py
tests/test_meshes2.py
tests/test_observer.py
tests/test_physical.py
tests/test_physicalgraph.py
tests/test_reader.py
tests/test_scene.py
tests/test_texture.py
ratcave-1.0.0.dist-info/LICENSE.txt
ratcave-1.0.0.dist-info/METADATA
ratcave-1.0.0.dist-info/WHEEL
ratcave-1.0.0.dist-info/top_level.txt
ratcave-1.0.0.dist-info/RECORD
