Metadata-Version: 2.1
Name: ratcave
Version: 1.0.0
Summary: 3D Graphics Engine for Scientific, Video Game, and VR Applications.
Home-page: https://www.github.com/neuroneuro15/ratcave
Author: Nicholas A. Del Grosso
Author-email: delgrosso.nick@gmail.com
License: MIT
Keywords: graphics 3D pyglet psychopy python virtual reality VR
Platform: UNKNOWN
Classifier: Topic :: Multimedia :: Graphics :: 3D Rendering
Classifier: Development Status :: 3 - Alpha
Classifier: License :: OSI Approved :: MIT License
Classifier: Intended Audience :: Science/Research
Classifier: Programming Language :: Python
Classifier: Programming Language :: Python :: 3
Classifier: Programming Language :: Python :: 3.3
Classifier: Programming Language :: Python :: 3.4
Classifier: Programming Language :: Python :: 3.5
Classifier: Programming Language :: Python :: 3.6
Classifier: Programming Language :: Python :: 3.7
Classifier: Programming Language :: Python :: 3.8
Requires-Dist: pyglet (==1.3.3)
Requires-Dist: numpy
Requires-Dist: scipy
Requires-Dist: wavefront-reader
